MANIFEST.in
README
setup.cfg
setup.py
modlit/__init__.py
modlit/api.py
modlit/base.py
modlit/errors.py
modlit/geometry.py
modlit/meta.py
modlit/model.py
modlit/modules.py
modlit/types.py
modlit.egg-info/PKG-INFO
modlit.egg-info/SOURCES.txt
modlit.egg-info/dependency_links.txt
modlit.egg-info/requires.txt
modlit.egg-info/top_level.txt
modlit/db/__init__.py
modlit/db/postgres.json
modlit/db/postgres.py
modlit/db/sqlalchemy.py
modlit/sphinx/__init__.py
modlit/sphinx/ext/__init__.py
modlit/sphinx/ext/modeldoc.py
modlit/sphinx/ext/monkeypatch.py
modlit/sphinx/ext/images/column.svg
modlit/sphinx/ext/images/curve.svg
modlit/sphinx/ext/images/geometry.svg
modlit/sphinx/ext/images/geometrycollection.svg
modlit/sphinx/ext/images/linestring.svg
modlit/sphinx/ext/images/multipoint.svg
modlit/sphinx/ext/images/multipolygon.svg
modlit/sphinx/ext/images/point.svg
modlit/sphinx/ext/images/polygon.svg
modlit/sphinx/ext/images/table.svg
modlit/testing/__init__.py
modlit/testing/postgres.py